bomweather/__init__.py
bomweather/forecast_stations.json
bomweather/forecasts.py
bomweather/obs_stations.json
bomweather/observations.py
bomweather/stations.py
bomweather-0.2.0.dist-info/LICENSE
bomweather-0.2.0.dist-info/METADATA
bomweather-0.2.0.dist-info/WHEEL
bomweather-0.2.0.dist-info/top_level.txt
bomweather-0.2.0.dist-info/RECORD
